quera/__init__.py
quera/utils/__init__.py
quera/utils/cache.py
quera/utils/drive.py
quera/utils/submit.py
quera/utils/validators.py
quera-0.1.16.dist-info/WHEEL
quera-0.1.16.dist-info/METADATA
quera-0.1.16.dist-info/RECORD
